mielib/__init__.py
mielib/extraspecial.py
mielib/harmonics.py
mielib/mieacoustics.py
mielib/mieoptics.py
mielib/rotations.py
mielib-0.1.12.dist-info/METADATA
mielib-0.1.12.dist-info/WHEEL
mielib-0.1.12.dist-info/RECORD
