Metadata-Version: 2.1
Name: mielib
Version: 0.1.12
Summary: Python library with many Mie-related functions for optics and acoustics
Home-page: https://github.com/toftul/mielib
License: MIT
Author: Ivan Toftul
Author-email: toftul.ivan@gmail.com
Requires-Python: >=3.10,<4.0
Classifier: License :: OSI Approved :: MIT License
Classifier: Programming Language :: Python :: 3
Classifier: Programming Language :: Python :: 3.10
Classifier: Programming Language :: Python :: 3.11
Requires-Dist: scipy (>=1.9.3,<2.0.0)
Project-URL: Repository, https://github.com/toftul/mielib
